{
  "frames": {
    "warrior-idle0.png": { "frame": { "x": 0, "y": 0, "w": 192, "h": 192 }, "rotated": false, "trimmed": false, "spriteSourceSize": { "x": 0, "y": 0, "w": 192, "h": 192 }, "sourceSize": { "w": 192, "h": 192 }, "duration": 100 },
    "warrior-idle1.png": { "frame": { "x": 192, "y": 0, "w": 192, "h": 192 }, "rotated": false, "trimmed": false, "spriteSourceSize": { "x": 0, "y": 0, "w": 192, "h": 192 }, "sourceSize": { "w": 192, "h": 192 }, "duration": 100 },
    "warrior-idle2.png": { "frame": { "x": 384, "y": 0, "w": 192, "h": 192 }, "rotated": false, "trimmed": false, "spriteSourceSize": { "x": 0, "y": 0, "w": 192, "h": 192 }, "sourceSize": { "w": 192, "h": 192 }, "duration": 100 },
    "warrior-idle3.png": { "frame": { "x": 576, "y": 0, "w": 192, "h": 192 }, "rotated": false, "trimmed": false, "spriteSourceSize": { "x": 0, "y": 0, "w": 192, "h": 192 }, "sourceSize": { "w": 192, "h": 192 }, "duration": 100 },
    "warrior-idle4.png": { "frame": { "x": 768, "y": 0, "w": 192, "h": 192 }, "rotated": false, "trimmed": false, "spriteSourceSize": { "x": 0, "y": 0, "w": 192, "h": 192 }, "sourceSize": { "w": 192, "h": 192 }, "duration": 100 },
    "warrior-idle5.png": { "frame": { "x": 960, "y": 0, "w": 192, "h": 192 }, "rotated": false, "trimmed": false, "spriteSourceSize": { "x": 0, "y": 0, "w": 192, "h": 192 }, "sourceSize": { "w": 192, "h": 192 }, "duration": 100 },
    "warrior-idle6.png": { "frame": { "x": 1152, "y": 0, "w": 192, "h": 192 }, "rotated": false, "trimmed": false, "spriteSourceSize": { "x": 0, "y": 0, "w": 192, "h": 192 }, "sourceSize": { "w": 192, "h": 192 }, "duration": 100 },
    "warrior-idle7.png": { "frame": { "x": 1344, "y": 0, "w": 192, "h": 192 }, "rotated": false, "trimmed": false, "spriteSourceSize": { "x": 0, "y": 0, "w": 192, "h": 192 }, "sourceSize": { "w": 192, "h": 192 }, "duration": 100 }
  },
  "meta": { "image": "warrior-idle.png", "format": "RGBA8888", "size": { "w": 1536, "h": 192 } }
}
